LICENSE.txt
MANIFEST.in
README.rst
setup.cfg
setup.py
pylastica/__init__.py
pylastica/client.py
pylastica/connection.py
pylastica/document.py
pylastica/log.py
pylastica/param.py
pylastica/percolator.py
pylastica/request.py
pylastica/response.py
pylastica/result.py
pylastica/resultset.py
pylastica/script.py
pylastica/scriptfields.py
pylastica/search.py
pylastica/searchable.py
pylastica/snapshot.py
pylastica/status.py
pylastica/util.py
pylastica.egg-info/PKG-INFO
pylastica.egg-info/SOURCES.txt
pylastica.egg-info/dependency_links.txt
pylastica.egg-info/requires.txt
pylastica.egg-info/top_level.txt
pylastica/aggregation/__init__.py
pylastica/aggregation/abstractaggregation.py
pylastica/aggregation/avg.py
pylastica/aggregation/datehistogram.py
pylastica/aggregation/daterange.py
pylastica/aggregation/extendedstats.py
pylastica/aggregation/filter.py
pylastica/aggregation/geodistance.py
pylastica/aggregation/geohashgrid.py
pylastica/aggregation/globalagg.py
pylastica/aggregation/histogram.py
pylastica/aggregation/iprange.py
pylastica/aggregation/max.py
pylastica/aggregation/min.py
pylastica/aggregation/missing.py
pylastica/aggregation/nested.py
pylastica/aggregation/range.py
pylastica/aggregation/stats.py
pylastica/aggregation/sum.py
pylastica/aggregation/terms.py
pylastica/aggregation/tophits.py
pylastica/aggregation/valuecount.py
pylastica/bulk/__init__.py
pylastica/bulk/response.py
pylastica/bulk/responseset.py
pylastica/bulk/action/__init__.py
pylastica/bulk/action/abstractdocument.py
pylastica/bulk/action/action.py
pylastica/bulk/action/createdocument.py
pylastica/bulk/action/deletedocument.py
pylastica/bulk/action/indexdocument.py
pylastica/bulk/action/updatedocument.py
pylastica/cluster/__init__.py
pylastica/cluster/settings.py
pylastica/cluster/health/__init__.py
pylastica/cluster/health/index.py
pylastica/cluster/health/shard.py
pylastica/doc_type/__init__.py
pylastica/doc_type/abstracttype.py
pylastica/doc_type/mapping.py
pylastica/exception/__init__.py
pylastica/exception/connection.py
pylastica/exception/bulk/__init__.py
pylastica/exception/bulk/response.py
pylastica/facet/__init__.py
pylastica/facet/abstractfacet.py
