Metadata-Version: 1.1
Name: pylastica
Version: 1.3.0.0
Summary: Python port of Nicolas Ruflin's Elastica PHP library
Home-page: https://github.com/jlinn/pylastica
Author: Joe Linn
Author-email: UNKNOWN
License: LICENSE.txt
Platform: UNKNOWN
Classifier: Intended Audience :: Developers
Classifier: Development Status :: 5 - Production/Stable
Classifier: Operating System :: OS Independent
Classifier: Programming Language :: Python
Classifier: Topic :: Internet :: WWW/HTTP :: Indexing/Search
